steam_reporter/__init__.py
steam_reporter/command_args.py
steam_reporter/config.py
steam_reporter/email_parser.py
steam_reporter/steam_reporter.py
steam_reporter/config/config.ini
steam_reporter-1.1.0.dist-info/METADATA
steam_reporter-1.1.0.dist-info/WHEEL
steam_reporter-1.1.0.dist-info/entry_points.txt
steam_reporter-1.1.0.dist-info/licenses/LICENSE
steam_reporter-1.1.0.dist-info/RECORD
