Metadata-Version: 2.1
Name: steam_reporter
Version: 1.1.0
Summary: A python tool for parsing and storing transaction information from steam market emails.
Project-URL: Homepage, https://github.com/bweissinger/steam-reporter
License: Copyright 2020 Bryan Weissinger
Classifier: License :: OSI Approved :: MIT License
Classifier: Operating System :: OS Independent
Classifier: Programming Language :: Python :: 3
Requires-Python: >=3.7
Requires-Dist: keyring
Requires-Dist: python-dateutil
